django_async_redis/__init__.py
django_async_redis/cache.py
django_async_redis/exceptions.py
django_async_redis/hash_ring.py
django_async_redis/pool.py
django_async_redis/util.py
django_async_redis/client/__init__.py
django_async_redis/client/default.py
django_async_redis/compressors/__init__.py
django_async_redis/compressors/base.py
django_async_redis/compressors/identity.py
django_async_redis/compressors/lz4.py
django_async_redis/compressors/lzma.py
django_async_redis/compressors/zlib.py
django_async_redis/compressors/zstd.py
django_async_redis/serializers/__init__.py
django_async_redis/serializers/base.py
django_async_redis/serializers/json.py
django_async_redis/serializers/msgpack.py
django_async_redis/serializers/pickle.py
django_async_redis-0.2.0.dist-info/AUTHORS.rst
django_async_redis-0.2.0.dist-info/LICENSE
django_async_redis-0.2.0.dist-info/METADATA
django_async_redis-0.2.0.dist-info/WHEEL
django_async_redis-0.2.0.dist-info/top_level.txt
django_async_redis-0.2.0.dist-info/RECORD
