Metadata-Version: 2.1
Name: django-async-redis
Version: 0.2.0
Summary: Full featured async Redis cache backend for Django.
Home-page: https://github.com/Andrew-Chen-Wang/django-async-redis
Author: Andrew Chen Wang
Author-email: acwangpython@gmail.com
License: Apache Software License 2.0
Keywords: django-async-redis
Classifier: Development Status :: 2 - Pre-Alpha
Classifier: Intended Audience :: Developers
Classifier: License :: OSI Approved :: Apache Software License
Classifier: Natural Language :: English
Classifier: Programming Language :: Python :: 3
Classifier: Programming Language :: Python :: 3.7
Classifier: Programming Language :: Python :: 3.8
Classifier: Programming Language :: Python :: 3.9
Classifier: Programming Language :: Python :: 3.10
Classifier: Programming Language :: Python :: 3.11
Classifier: Framework :: Django :: 3.2
Classifier: Framework :: Django :: 4.1
Requires-Python: >=3.7
License-File: LICENSE
License-File: AUTHORS.rst
Requires-Dist: django (>=3.2)
Requires-Dist: redis (>=4.2.0)
